{
    "background": {
        "color": {
            "value": "#f9f9f9"
        },
        "image": "",
        "position": "50% 50%",
        "repeat": "no-repeat",
        "size": "cover",
        "opacity": 1
    },
    "particles": {
        "number": {
            "value": 120,
            "density": {
                "enable": true,
                "area": 1200
            }
        },
        "color": {
            "value": ["#ff8c00", "#ffa500", "#ffd700", "#f0e68c", "#fffacd", "#ffe4b5"]
        },
        "shape": {
            "type": "image",
            "image": {
                "src": "/butterfly.webp",
                "width": 60,
                "height": 60
            },
            "options": {
                "polygon": {
                    "sides": 5
                }
            }
        },
        "opacity": {
            "value": {
                "min": 0.3,
                "max": 0.8
            },
            "random": true,
            "animation": {
                "enable": true,
                "speed": 2,
                "minimumValue": 0.3,
                "sync": false
            }
        },
        "size": {
            "value": {
                "min": 12,
                "max": 25
            },
            "random": true,
            "animation": {
                "enable": true,
                "speed": 3,
                "minimumValue": 10,
                "sync": false
            }
        },
        "move": {
            "enable": true,
            "speed": 2.5,
            "direction": "top-right",
            "outModes": {
                "default": "out",
                "bottom": "bounce"
            },
            "random": false,
            "straight": false,
            "path": {
                "enable": true,
                "options": {}
            },
            "trail": {
                "enable": true,
                "length": 5,
                "fillColor": "#ffffff"
            }
        },
        "links": {
            "enable": true,
            "distance": 120,
            "color": "#ffa500",
            "opacity": 0.5,
            "width": 1
        }
    },
    "interactivity": {
        "events": {
            "onHover": {
                "enable": true,
                "mode": ["grab", "bubble"],
                "parallax": {
                    "enable": false,
                    "force": 60,
                    "smooth": 10
                }
            },
            "onClick": {
                "enable": true,
                "mode": ["bubble", "push", "repulse"]
            },
            "resize": true
        },
        "modes": {
            "grab": {
                "distance": 250,
                "links": {
                    "opacity": 0.7
                }
            },
            "bubble": {
                "distance": 200,
                "size": 35,
                "duration": 3,
                "opacity": 1
            },
            "repulse": {
                "distance": 150,
                "duration": 0.5
            },
            "push": {
                "quantity": 8
            },
            "remove": {
                "quantity": 4
            }
        }
    },
    "fullScreen": {
        "enable": true,
        "zIndex": -1
    },
    "detectRetina": true,
    "fpsLimit": 90,
    "smooth": true,
    "pauseOnBlur": true,
    "pauseOnOutsideViewport": true,
    "themes": [
        {
            "name": "light",
            "options": {
                "background": {
                    "color": "#ffffff"
                }
            }
        },
        {
            "name": "dark",
            "options": {
                "background": {
                    "color": "#000000"
                },
                "particles": {
                    "color": {
                        "value": ["#ffffff", "#aaaaaa"]
                    }
                }
            }
        }
    ]
}
